localvenv_kernel/__init__.py
localvenv_kernel/__main__.py
localvenv_kernel/kernelspec.py
python_localvenv_kernel-0.1.7.data/data/share/jupyter/kernels/python-localvenv/kernel.json
python_localvenv_kernel-0.1.7.dist-info/LICENSE.md
python_localvenv_kernel-0.1.7.dist-info/METADATA
python_localvenv_kernel-0.1.7.dist-info/WHEEL
python_localvenv_kernel-0.1.7.dist-info/top_level.txt
python_localvenv_kernel-0.1.7.dist-info/RECORD
